.coveragerc
.gitignore
.travis.yml
LICENSE.txt
MANIFEST.in
README.rst
bootstrap.py
bootstrap.sh
buildout.cfg
ez_setup.py
requirements.txt
setup.cfg
setup.py
versions.cfg
openprocurement/__init__.py
openprocurement.edge.egg-info/PKG-INFO
openprocurement.edge.egg-info/SOURCES.txt
openprocurement.edge.egg-info/dependency_links.txt
openprocurement.edge.egg-info/entry_points.txt
openprocurement.edge.egg-info/namespace_packages.txt
openprocurement.edge.egg-info/not-zip-safe
openprocurement.edge.egg-info/requires.txt
openprocurement.edge.egg-info/top_level.txt
openprocurement/edge/__init__.py
openprocurement/edge/databridge.py
openprocurement/edge/design.py
openprocurement/edge/main.py
openprocurement/edge/traversal.py
openprocurement/edge/utils.py
openprocurement/edge/workers.py
openprocurement/edge/couch_views/auctions/.couchapprc
openprocurement/edge/couch_views/auctions/_id
openprocurement/edge/couch_views/auctions/language
openprocurement/edge/couch_views/auctions/options/local_seq.json
openprocurement/edge/couch_views/auctions/shows/show.js
openprocurement/edge/couch_views/auctions/views/all/map.js
openprocurement/edge/couch_views/auctions/views/by_dateModified/map.js
openprocurement/edge/couch_views/auctions/views/by_local_seq/map.js
openprocurement/edge/couch_views/auctions/views/real_by_dateModified/map.js
openprocurement/edge/couch_views/auctions/views/real_by_local_seq/map.js
openprocurement/edge/couch_views/auctions/views/test_by_dateModified/map.js
openprocurement/edge/couch_views/auctions/views/test_by_local_seq/map.js
openprocurement/edge/couch_views/contracts/.couchapprc
openprocurement/edge/couch_views/contracts/_id
openprocurement/edge/couch_views/contracts/language
openprocurement/edge/couch_views/contracts/options/local_seq.json
openprocurement/edge/couch_views/contracts/shows/show.js
openprocurement/edge/couch_views/contracts/views/all/map.js
openprocurement/edge/couch_views/contracts/views/by_dateModified/map.js
openprocurement/edge/couch_views/contracts/views/by_local_seq/map.js
openprocurement/edge/couch_views/contracts/views/real_by_dateModified/map.js
openprocurement/edge/couch_views/contracts/views/real_by_local_seq/map.js
openprocurement/edge/couch_views/contracts/views/test_by_dateModified/map.js
openprocurement/edge/couch_views/contracts/views/test_by_local_seq/map.js
