Metadata-Version: 1.1
Name: openprocurement.edge
Version: 1.0.0
Summary: openprocurement.edge
Home-page: https://github.com/openprocurement/openprocurement.edge
Author: Quintagroup, Ltd.
Author-email: info@quintagroup.com
License: Apache License 2.0
Keywords: web services
Platform: UNKNOWN
Classifier: Framework :: Pylons
Classifier: License :: OSI Approved :: Apache Software License
Classifier: Programming Language :: Python
Classifier: Topic :: Internet :: WWW/HTTP
Classifier: Topic :: Internet :: WWW/HTTP :: WSGI :: Application
